agatemdb/__init__.py
agatemdb/table_mdb.py
agate_mdb-0.0.3.dist-info/AUTHORS.rst
agate_mdb-0.0.3.dist-info/COPYING
agate_mdb-0.0.3.dist-info/METADATA
agate_mdb-0.0.3.dist-info/WHEEL
agate_mdb-0.0.3.dist-info/top_level.txt
agate_mdb-0.0.3.dist-info/RECORD
