Metadata-Version: 2.1
Name: agate-mdb
Version: 0.0.3
Summary: agate-mdb adds read support for Microsoft Access files to agate.
Home-page: http://agate-mdb.readthedocs.org/
Author: Loïc Corbasson
Author-email: loic.corbasson@gmail.com
License: MIT
Platform: UNKNOWN
Classifier: Development Status :: 4 - Beta
Classifier: Intended Audience :: Developers
Classifier: Intended Audience :: Science/Research
Classifier: License :: OSI Approved :: MIT License
Classifier: Natural Language :: English
Classifier: Operating System :: OS Independent
Classifier: Programming Language :: Python
Classifier: Programming Language :: Python :: 3.7
Classifier: Programming Language :: Python :: 3.8
Classifier: Programming Language :: Python :: 3.9
Classifier: Programming Language :: Python :: Implementation :: CPython
Classifier: Programming Language :: Python :: Implementation :: PyPy
Classifier: Topic :: Scientific/Engineering :: Information Analysis
Classifier: Topic :: Software Development :: Libraries :: Python Modules
License-File: COPYING
License-File: AUTHORS.rst
Requires-Dist: agate (>=1.5.0)
Provides-Extra: docs
Requires-Dist: Sphinx (>=1.2.2) ; extra == 'docs'
Requires-Dist: sphinx-rtd-theme (>=0.1.6) ; extra == 'docs'
Provides-Extra: test
Requires-Dist: nose (>=1.1.2) ; extra == 'test'
